[
  {
    "A_name" : "ObservableType",
    "B_kind" : "extension",
    "C_accessLevel" : "internal",
    "D_attributes" : [

    ],
    "E_adoptedClassProtocols" : [

    ],
    "F_location" : "Map.swift - Line: 9, Column: 1",
    "G_members" : [
      {
        "A_name" : "map",
        "B_kind" : "function",
        "C_accessLevel" : "public",
        "D_attributes" : [

        ],
        "F_location" : "Map.swift - Line: 20, Column: 5",
        "G_members" : [

        ],
        "I_parameterType" : [
          "@escaping (Element) throws -> Result"
        ],
        "I_parameters" : [
          "_"
        ],
        "J_returnType" : "-> Observable<Result>"
      }
    ]
  },
  {
    "A_name" : "map",
    "B_kind" : "function",
    "C_accessLevel" : "public",
    "D_attributes" : [

    ],
    "F_location" : "Map.swift - Line: 20, Column: 5",
    "G_members" : [

    ],
    "I_parameterType" : [
      "@escaping (Element) throws -> Result"
    ],
    "I_parameters" : [
      "_"
    ],
    "J_returnType" : "-> Observable<Result>"
  },
  {
    "A_name" : "MapSink",
    "B_kind" : "class",
    "C_accessLevel" : "final",
    "D_attributes" : [
      "final"
    ],
    "E_adoptedClassProtocols" : [
      "Sink<Observer>",
      "ObserverType"
    ],
    "F_location" : "Map.swift - Line: 26, Column: 1",
    "G_members" : [
      {
        "A_name" : "transform",
        "B_kind" : "variable",
        "C_accessLevel" : "private",
        "D_attributes" : [

        ],
        "F_location" : "Map.swift - Line: 32, Column: 5",
        "H_initialValue" : ""
      },
      {
        "A_name" : "init",
        "B_kind" : "function",
        "C_accessLevel" : "internal",
        "D_attributes" : [

        ],
        "F_location" : "Map.swift - Line: 34, Column: 5",
        "G_members" : [

        ],
        "I_parameterType" : [
          "@escaping Transform",
          "Observer",
          "Cancelable"
        ],
        "I_parameters" : [
          "transform",
          "observer",
          "cancel"
        ]
      },
      {
        "A_name" : "on",
        "B_kind" : "function",
        "C_accessLevel" : "internal",
        "D_attributes" : [

        ],
        "F_location" : "Map.swift - Line: 39, Column: 5",
        "G_members" : [

        ],
        "I_parameterType" : [
          "Event<SourceType>"
        ],
        "I_parameters" : [
          "_"
        ]
      }
    ]
  },
  {
    "A_name" : "transform",
    "B_kind" : "variable",
    "C_accessLevel" : "private",
    "D_attributes" : [

    ],
    "F_location" : "Map.swift - Line: 32, Column: 5",
    "H_initialValue" : ""
  },
  {
    "A_name" : "init",
    "B_kind" : "function",
    "C_accessLevel" : "internal",
    "D_attributes" : [

    ],
    "F_location" : "Map.swift - Line: 34, Column: 5",
    "G_members" : [

    ],
    "I_parameterType" : [
      "@escaping Transform",
      "Observer",
      "Cancelable"
    ],
    "I_parameters" : [
      "transform",
      "observer",
      "cancel"
    ]
  },
  {
    "A_name" : "on",
    "B_kind" : "function",
    "C_accessLevel" : "internal",
    "D_attributes" : [

    ],
    "F_location" : "Map.swift - Line: 39, Column: 5",
    "G_members" : [

    ],
    "I_parameterType" : [
      "Event<SourceType>"
    ],
    "I_parameters" : [
      "_"
    ]
  },
  {
    "A_name" : "mappedElement",
    "B_kind" : "variable",
    "C_accessLevel" : "internal",
    "D_attributes" : [

    ],
    "F_location" : "Map.swift - Line: 43, Column: 17",
    "H_initialValue" : "try self.transform(element)"
  },
  {
    "A_name" : "Map",
    "B_kind" : "class",
    "C_accessLevel" : "final",
    "D_attributes" : [
      "final"
    ],
    "E_adoptedClassProtocols" : [
      "Producer<ResultType>"
    ],
    "F_location" : "Map.swift - Line: 60, Column: 1",
    "G_members" : [
      {
        "A_name" : "source",
        "B_kind" : "variable",
        "C_accessLevel" : "private",
        "D_attributes" : [

        ],
        "F_location" : "Map.swift - Line: 63, Column: 5",
        "H_initialValue" : ""
      },
      {
        "A_name" : "transform",
        "B_kind" : "variable",
        "C_accessLevel" : "private",
        "D_attributes" : [

        ],
        "F_location" : "Map.swift - Line: 65, Column: 5",
        "H_initialValue" : ""
      },
      {
        "A_name" : "init",
        "B_kind" : "function",
        "C_accessLevel" : "internal",
        "D_attributes" : [

        ],
        "F_location" : "Map.swift - Line: 67, Column: 5",
        "G_members" : [

        ],
        "I_parameterType" : [
          "Observable<SourceType>",
          "@escaping Transform"
        ],
        "I_parameters" : [
          "source",
          "transform"
        ]
      },
      {
        "A_name" : "run",
        "B_kind" : "function",
        "C_accessLevel" : "override",
        "D_attributes" : [
          "override"
        ],
        "F_location" : "Map.swift - Line: 72, Column: 5",
        "G_members" : [
          {
            "A_name" : "sink",
            "B_kind" : "variable",
            "C_accessLevel" : "internal",
            "D_attributes" : [

            ],
            "F_location" : "Map.swift - Line: 73, Column: 9",
            "H_initialValue" : "MapSink(transform: self.transform, observer: observer, cancel: cancel)"
          },
          {
            "A_name" : "subscription",
            "B_kind" : "variable",
            "C_accessLevel" : "internal",
            "D_attributes" : [

            ],
            "F_location" : "Map.swift - Line: 74, Column: 9",
            "H_initialValue" : "self.source.subscribe(sink)"
          }
        ],
        "I_parameterType" : [
          "Observer",
          "Cancelable"
        ],
        "I_parameters" : [
          "_",
          "cancel"
        ],
        "J_returnType" : "-> (sink: Disposable, subscription: Disposable)"
      }
    ]
  },
  {
    "A_name" : "source",
    "B_kind" : "variable",
    "C_accessLevel" : "private",
    "D_attributes" : [

    ],
    "F_location" : "Map.swift - Line: 63, Column: 5",
    "H_initialValue" : ""
  },
  {
    "A_name" : "transform",
    "B_kind" : "variable",
    "C_accessLevel" : "private",
    "D_attributes" : [

    ],
    "F_location" : "Map.swift - Line: 65, Column: 5",
    "H_initialValue" : ""
  },
  {
    "A_name" : "init",
    "B_kind" : "function",
    "C_accessLevel" : "internal",
    "D_attributes" : [

    ],
    "F_location" : "Map.swift - Line: 67, Column: 5",
    "G_members" : [

    ],
    "I_parameterType" : [
      "Observable<SourceType>",
      "@escaping Transform"
    ],
    "I_parameters" : [
      "source",
      "transform"
    ]
  },
  {
    "A_name" : "run",
    "B_kind" : "function",
    "C_accessLevel" : "override",
    "D_attributes" : [
      "override"
    ],
    "F_location" : "Map.swift - Line: 72, Column: 5",
    "G_members" : [
      {
        "A_name" : "sink",
        "B_kind" : "variable",
        "C_accessLevel" : "internal",
        "D_attributes" : [

        ],
        "F_location" : "Map.swift - Line: 73, Column: 9",
        "H_initialValue" : "MapSink(transform: self.transform, observer: observer, cancel: cancel)"
      },
      {
        "A_name" : "subscription",
        "B_kind" : "variable",
        "C_accessLevel" : "internal",
        "D_attributes" : [

        ],
        "F_location" : "Map.swift - Line: 74, Column: 9",
        "H_initialValue" : "self.source.subscribe(sink)"
      }
    ],
    "I_parameterType" : [
      "Observer",
      "Cancelable"
    ],
    "I_parameters" : [
      "_",
      "cancel"
    ],
    "J_returnType" : "-> (sink: Disposable, subscription: Disposable)"
  },
  {
    "A_name" : "sink",
    "B_kind" : "variable",
    "C_accessLevel" : "internal",
    "D_attributes" : [

    ],
    "F_location" : "Map.swift - Line: 73, Column: 9",
    "H_initialValue" : "MapSink(transform: self.transform, observer: observer, cancel: cancel)"
  },
  {
    "A_name" : "subscription",
    "B_kind" : "variable",
    "C_accessLevel" : "internal",
    "D_attributes" : [

    ],
    "F_location" : "Map.swift - Line: 74, Column: 9",
    "H_initialValue" : "self.source.subscribe(sink)"
  }
]