[
  {
    "size": 10,
    "rep": "StringResource",
    "tokens": [
      "resource",
      "resource1",
      "resource2",
      "resource3",
      "resource4",
      "resource5",
      "resource6",
      "resource7",
      "resource8",
      "resource9",
      "string"
    ],
    "members": [
      "StringResource",
      "StringResource1",
      "StringResource2",
      "StringResource3",
      "StringResource4",
      "StringResource5",
      "StringResource6",
      "StringResource7",
      "StringResource8",
      "StringResource9"
    ]
  },
  {
    "size": 9,
    "rep": "CompoundNode",
    "tokens": [
      "compound",
      "node",
      "node2",
      "node3",
      "node4",
      "node5",
      "node6",
      "node7",
      "node8",
      "node9"
    ],
    "members": [
      "CompoundNode",
      "CompoundNode2",
      "CompoundNode3",
      "CompoundNode4",
      "CompoundNode5",
      "CompoundNode6",
      "CompoundNode7",
      "CompoundNode8",
      "CompoundNode9"
    ]
  },
  {
    "size": 9,
    "rep": "TupleView",
    "tokens": [
      "tuple",
      "view",
      "view2",
      "view3",
      "view4",
      "view5",
      "view6",
      "view7",
      "view8",
      "view9"
    ],
    "members": [
      "TupleView",
      "TupleView2",
      "TupleView3",
      "TupleView4",
      "TupleView5",
      "TupleView6",
      "TupleView7",
      "TupleView8",
      "TupleView9"
    ]
  },
  {
    "size": 8,
    "rep": "Fuzzilli_Protobuf_Wasmi32UnOp",
    "tokens": [
      "fuzzilli",
      "op",
      "protobuf",
      "wasmf32bin",
      "wasmf32un",
      "wasmf64bin",
      "wasmf64un",
      "wasmi32bin",
      "wasmi32un",
      "wasmi64bin",
      "wasmi64un"
    ],
    "members": [
      "Fuzzilli_Protobuf_Wasmf32BinOp",
      "Fuzzilli_Protobuf_Wasmf32UnOp",
      "Fuzzilli_Protobuf_Wasmf64BinOp",
      "Fuzzilli_Protobuf_Wasmf64UnOp",
      "Fuzzilli_Protobuf_Wasmi32BinOp",
      "Fuzzilli_Protobuf_Wasmi32UnOp",
      "Fuzzilli_Protobuf_Wasmi64BinOp",
      "Fuzzilli_Protobuf_Wasmi64UnOp"
    ]
  },
  {
    "size": 7,
    "rep": "CoreAppModule",
    "tokens": [
      "app",
      "core",
      "module",
      "module2",
      "module3",
      "module4",
      "module5",
      "module6",
      "module7"
    ],
    "members": [
      "CoreAppModule",
      "CoreAppModule2",
      "CoreAppModule3",
      "CoreAppModule4",
      "CoreAppModule5",
      "CoreAppModule6",
      "CoreAppModule7"
    ]
  },
  {
    "size": 5,
    "rep": "Fuzzilli_Protobuf_WasmTruncatef64Toi32",
    "tokens": [
      "fuzzilli",
      "protobuf",
      "truncatef32toi32",
      "truncatef32toi64",
      "truncatef64toi32",
      "truncatef64toi64",
      "truncatei64tof32",
      "wasm"
    ],
    "members": [
      "Fuzzilli_Protobuf_WasmTruncatef32Toi32",
      "Fuzzilli_Protobuf_WasmTruncatef32Toi64",
      "Fuzzilli_Protobuf_WasmTruncatef64Toi32",
      "Fuzzilli_Protobuf_WasmTruncatef64Toi64",
      "Fuzzilli_Protobuf_WasmTruncatei64Tof32"
    ]
  },
  {
    "size": 5,
    "rep": "GeneratorAdapter2Args",
    "tokens": [
      "adapter",
      "adapter1arg",
      "adapter2args",
      "adapter3args",
      "adapter4args",
      "args",
      "generator",
      "no"
    ],
    "members": [
      "GeneratorAdapter1Arg",
      "GeneratorAdapter2Args",
      "GeneratorAdapter3Args",
      "GeneratorAdapter4Args",
      "GeneratorAdapterNoArgs"
    ]
  },
  {
    "size": 5,
    "rep": "Preview",
    "tokens": [
      "preview",
      "preview2",
      "preview3",
      "previews",
      "s"
    ],
    "members": [
      "Preview",
      "Preview2",
      "Preview3",
      "PreviewS",
      "Previews"
    ]
  },
  {
    "size": 4,
    "rep": "BenchDocBuilder",
    "tokens": [
      "bench",
      "builder",
      "doc",
      "v2builder",
      "v3builder",
      "v4builder"
    ],
    "members": [
      "BenchDocBuilder",
      "BenchDocV2Builder",
      "BenchDocV3Builder",
      "BenchDocV4Builder"
    ]
  },
  {
    "size": 4,
    "rep": "Device",
    "tokens": [
      "device",
      "devices",
      "s"
    ],
    "members": [
      "Device",
      "Devices",
      "device",
      "device_s"
    ]
  },
  {
    "size": 4,
    "rep": "Fuzzilli_Protobuf_EndForLoop",
    "tokens": [
      "begin",
      "end",
      "for",
      "fuzzilli",
      "in",
      "loop",
      "of",
      "protobuf"
    ],
    "members": [
      "Fuzzilli_Protobuf_BeginForOfLoop",
      "Fuzzilli_Protobuf_EndForInLoop",
      "Fuzzilli_Protobuf_EndForLoop",
      "Fuzzilli_Protobuf_EndForOfLoop"
    ]
  },
  {
    "size": 4,
    "rep": "Fuzzilli_Protobuf_WasmConverti32Tof64",
    "tokens": [
      "converti32tof32",
      "converti32tof64",
      "converti64tof32",
      "converti64tof64",
      "fuzzilli",
      "protobuf",
      "wasm"
    ],
    "members": [
      "Fuzzilli_Protobuf_WasmConverti32Tof32",
      "Fuzzilli_Protobuf_WasmConverti32Tof64",
      "Fuzzilli_Protobuf_WasmConverti64Tof32",
      "Fuzzilli_Protobuf_WasmConverti64Tof64"
    ]
  },
  {
    "size": 4,
    "rep": "Fuzzilli_Protobuf_Wasmf32CompareOp",
    "tokens": [
      "fuzzilli",
      "op",
      "protobuf",
      "wasmf32compare",
      "wasmf64compare",
      "wasmi32compare",
      "wasmi64compare"
    ],
    "members": [
      "Fuzzilli_Protobuf_Wasmf32CompareOp",
      "Fuzzilli_Protobuf_Wasmf64CompareOp",
      "Fuzzilli_Protobuf_Wasmi32CompareOp",
      "Fuzzilli_Protobuf_Wasmi64CompareOp"
    ]
  },
  {
    "size": 4,
    "rep": "SampleView",
    "tokens": [
      "sample",
      "sample1view",
      "sample2view",
      "sampler",
      "view"
    ],
    "members": [
      "Sample1View",
      "Sample2View",
      "SampleView",
      "SamplerView"
    ]
  },
  {
    "size": 4,
    "rep": "zzz_DflatGen_BenchDoc",
    "tokens": [
      "bench",
      "dflat",
      "doc",
      "gen",
      "v2",
      "v3",
      "v4",
      "zzz"
    ],
    "members": [
      "zzz_DflatGen_BenchDoc",
      "zzz_DflatGen_BenchDocV2",
      "zzz_DflatGen_BenchDocV3",
      "zzz_DflatGen_BenchDocV4"
    ]
  },
  {
    "size": 3,
    "rep": "CombineLatest",
    "tokens": [
      "combine",
      "latest",
      "latest3",
      "latest4"
    ],
    "members": [
      "CombineLatest",
      "CombineLatest3",
      "CombineLatest4"
    ]
  },
  {
    "size": 3,
    "rep": "Compiler_Protobuf_ForLoop",
    "tokens": [
      "compiler",
      "for",
      "in",
      "loop",
      "of",
      "protobuf"
    ],
    "members": [
      "Compiler_Protobuf_ForInLoop",
      "Compiler_Protobuf_ForLoop",
      "Compiler_Protobuf_ForOfLoop"
    ]
  },
  {
    "size": 3,
    "rep": "DuoFireworks1_Previews",
    "tokens": [
      "duo",
      "fireworks1",
      "fireworks2",
      "fireworks3",
      "previews"
    ],
    "members": [
      "DuoFireworks1_Previews",
      "DuoFireworks2_Previews",
      "DuoFireworks3_Previews"
    ]
  },
  {
    "size": 3,
    "rep": "EaseInOutExample_Previews",
    "tokens": [
      "ease",
      "example",
      "in",
      "out",
      "previews"
    ],
    "members": [
      "EaseInExample_Previews",
      "EaseInOutExample_Previews",
      "EaseOutExample_Previews"
    ]
  },
  {
    "size": 3,
    "rep": "Example1ContentView",
    "tokens": [
      "example1content",
      "example2content",
      "example3content",
      "view"
    ],
    "members": [
      "Example1ContentView",
      "Example2ContentView",
      "Example3ContentView"
    ]
  },
  {
    "size": 3,
    "rep": "Example1ContentView_Previews",
    "tokens": [
      "example1content",
      "example2content",
      "example3content",
      "previews",
      "view"
    ],
    "members": [
      "Example1ContentView_Previews",
      "Example2ContentView_Previews",
      "Example3ContentView_Previews"
    ]
  },
  {
    "size": 3,
    "rep": "Fuzzilli_Protobuf_CreateWasmTag",
    "tokens": [
      "create",
      "fuzzilli",
      "jstag",
      "protobuf",
      "table",
      "tag",
      "wasm"
    ],
    "members": [
      "Fuzzilli_Protobuf_CreateWasmJSTag",
      "Fuzzilli_Protobuf_CreateWasmTable",
      "Fuzzilli_Protobuf_CreateWasmTag"
    ]
  },
  {
    "size": 3,
    "rep": "LottieVector1D",
    "tokens": [
      "lottie",
      "vector1d",
      "vector2d",
      "vector3d"
    ],
    "members": [
      "LottieVector1D",
      "LottieVector2D",
      "LottieVector3D"
    ]
  },
  {
    "size": 3,
    "rep": "MapKeyPath",
    "tokens": [
      "key",
      "map",
      "path",
      "path2",
      "path3"
    ],
    "members": [
      "MapKeyPath",
      "MapKeyPath2",
      "MapKeyPath3"
    ]
  },
  {
    "size": 3,
    "rep": "Module",
    "tokens": [
      "c",
      "module",
      "modules"
    ],
    "members": [
      "Module",
      "Modules",
      "module_c"
    ]
  },
  {
    "size": 3,
    "rep": "RelativeOffsetProvider",
    "tokens": [
      "offset",
      "provider",
      "relative",
      "xoffset",
      "yoffset"
    ],
    "members": [
      "RelativeOffsetProvider",
      "RelativeXOffsetProvider",
      "RelativeYOffsetProvider"
    ]
  },
  {
    "size": 3,
    "rep": "ResizeToFit",
    "tokens": [
      "fit",
      "fit1",
      "fit2",
      "resize",
      "to"
    ],
    "members": [
      "ResizeToFit",
      "ResizeToFit1",
      "ResizeToFit2"
    ]
  },
  {
    "size": 3,
    "rep": "Sensor",
    "tokens": [
      "sensor",
      "t",
      "w"
    ],
    "members": [
      "Sensor",
      "Sensor_t",
      "Sensor_w"
    ]
  },
  {
    "size": 3,
    "rep": "Skid_Previews",
    "tokens": [
      "2",
      "preview",
      "previews",
      "skid"
    ],
    "members": [
      "Skid_2_Previews",
      "Skid_Preview",
      "Skid_Previews"
    ]
  },
  {
    "size": 3,
    "rep": "SwiftPackage",
    "tokens": [
      "package",
      "swift",
      "v1",
      "v2"
    ],
    "members": [
      "SwiftPackage",
      "SwiftPackageV1",
      "SwiftPackageV2"
    ]
  },
  {
    "size": 3,
    "rep": "TryCombineLatest",
    "tokens": [
      "combine",
      "latest",
      "latest3",
      "latest4",
      "try"
    ],
    "members": [
      "TryCombineLatest",
      "TryCombineLatest3",
      "TryCombineLatest4"
    ]
  },
  {
    "size": 3,
    "rep": "Widgets",
    "tokens": [
      "c",
      "s",
      "widget",
      "widgets"
    ],
    "members": [
      "Widget",
      "Widget_c_s",
      "Widgets"
    ]
  },
  {
    "size": 3,
    "rep": "zzz_DflatGen_MyGame_SampleV2_Monster",
    "tokens": [
      "dflat",
      "game",
      "gen",
      "monster",
      "my",
      "sample",
      "v2",
      "v3",
      "zzz"
    ],
    "members": [
      "zzz_DflatGen_MyGame_SampleV2_Monster",
      "zzz_DflatGen_MyGame_SampleV3_Monster",
      "zzz_DflatGen_MyGame_Sample_Monster"
    ]
  },
  {
    "size": 3,
    "rep": "zzz_DflatGen_MyGame_SampleV2_Orb",
    "tokens": [
      "dflat",
      "game",
      "gen",
      "my",
      "orb",
      "sample",
      "v2",
      "v3",
      "zzz"
    ],
    "members": [
      "zzz_DflatGen_MyGame_SampleV2_Orb",
      "zzz_DflatGen_MyGame_SampleV3_Orb",
      "zzz_DflatGen_MyGame_Sample_Orb"
    ]
  },
  {
    "size": 3,
    "rep": "zzz_DflatGen_MyGame_Sample_Vec3",
    "tokens": [
      "dflat",
      "game",
      "gen",
      "my",
      "sample",
      "v2",
      "v3",
      "vec3",
      "zzz"
    ],
    "members": [
      "zzz_DflatGen_MyGame_SampleV2_Vec3",
      "zzz_DflatGen_MyGame_SampleV3_Vec3",
      "zzz_DflatGen_MyGame_Sample_Vec3"
    ]
  },
  {
    "size": 3,
    "rep": "zzz_DflatGen_MyGame_SampleV2_Weapon",
    "tokens": [
      "dflat",
      "game",
      "gen",
      "my",
      "sample",
      "v2",
      "v3",
      "weapon",
      "zzz"
    ],
    "members": [
      "zzz_DflatGen_MyGame_SampleV2_Weapon",
      "zzz_DflatGen_MyGame_SampleV3_Weapon",
      "zzz_DflatGen_MyGame_Sample_Weapon"
    ]
  },
  {
    "size": 2,
    "rep": "AboutViewPreview",
    "tokens": [
      "about",
      "preview",
      "previews",
      "view"
    ],
    "members": [
      "AboutViewPreview",
      "AboutView_Previews"
    ]
  },
  {
    "size": 2,
    "rep": "AccessibilityIdentifier",
    "tokens": [
      "accessibility",
      "identifier",
      "identifiers"
    ],
    "members": [
      "AccessibilityIdentifier",
      "AccessibilityIdentifiers"
    ]
  },
  {
    "size": 2,
    "rep": "Action",
    "tokens": [
      "action",
      "actions"
    ],
    "members": [
      "Action",
      "Actions"
    ]
  },
  {
    "size": 2,
    "rep": "Analyze",
    "tokens": [
      "analyze",
      "analyzer"
    ],
    "members": [
      "Analyze",
      "Analyzer"
    ]
  },
  {
    "size": 2,
    "rep": "AnimationOption",
    "tokens": [
      "animation",
      "option",
      "options"
    ],
    "members": [
      "AnimationOption",
      "AnimationOptions"
    ]
  },
  {
    "size": 2,
    "rep": "AnimationOptionView",
    "tokens": [
      "animation",
      "option",
      "options",
      "view"
    ],
    "members": [
      "AnimationOptionView",
      "AnimationOptionsView"
    ]
  },
  {
    "size": 2,
    "rep": "AnimationParameter",
    "tokens": [
      "animation",
      "parameter",
      "parameters"
    ],
    "members": [
      "AnimationParameter",
      "AnimationParameters"
    ]
  },
  {
    "size": 2,
    "rep": "Anvil_Preview",
    "tokens": [
      "anvil",
      "preview",
      "previews"
    ],
    "members": [
      "Anvil_Preview",
      "Anvil_Previews"
    ]
  },
  {
    "size": 2,
    "rep": "API",
    "tokens": [
      "api"
    ],
    "members": [
      "API",
      "Api"
    ]
  },
  {
    "size": 2,
    "rep": "AppearanceSettingView",
    "tokens": [
      "appearance",
      "setting",
      "settings",
      "view"
    ],
    "members": [
      "AppearanceSettingView",
      "AppearanceSettingsView"
    ]
  },
  {
    "size": 2,
    "rep": "AppStoreAccountAddView",
    "tokens": [
      "account",
      "add",
      "app",
      "store",
      "view"
    ],
    "members": [
      "AppStoreAccountAddView",
      "AppStoreAccountView"
    ]
  },
  {
    "size": 2,
    "rep": "Argument",
    "tokens": [
      "argument",
      "arguments"
    ],
    "members": [
      "Argument",
      "Arguments"
    ]
  },
  {
    "size": 2,
    "rep": "AspectScaledToFillSizeFilter",
    "tokens": [
      "aspect",
      "fill",
      "filter",
      "fit",
      "scaled",
      "size",
      "to"
    ],
    "members": [
      "AspectScaledToFillSizeFilter",
      "AspectScaledToFitSizeFilter"
    ]
  },
  {
    "size": 2,
    "rep": "AssetCatalog",
    "tokens": [
      "asset",
      "assets",
      "catalog"
    ],
    "members": [
      "AssetCatalog",
      "AssetsCatalog"
    ]
  },
  {
    "size": 2,
    "rep": "AsyncChain2Sequence",
    "tokens": [
      "async",
      "chain2sequence",
      "chain3sequence"
    ],
    "members": [
      "AsyncChain2Sequence",
      "AsyncChain3Sequence"
    ]
  },
  {
    "size": 2,
    "rep": "AsyncCombineLatest2Sequence",
    "tokens": [
      "async",
      "combine",
      "latest2sequence",
      "latest3sequence"
    ],
    "members": [
      "AsyncCombineLatest2Sequence",
      "AsyncCombineLatest3Sequence"
    ]
  },
  {
    "size": 2,
    "rep": "AsyncMerge2Sequence",
    "tokens": [
      "async",
      "merge2sequence",
      "merge3sequence"
    ],
    "members": [
      "AsyncMerge2Sequence",
      "AsyncMerge3Sequence"
    ]
  },
  {
    "size": 2,
    "rep": "AsyncZip2Sequence",
    "tokens": [
      "async",
      "zip2sequence",
      "zip3sequence"
    ],
    "members": [
      "AsyncZip2Sequence",
      "AsyncZip3Sequence"
    ]
  },
  {
    "size": 2,
    "rep": "ATBottomTopEffect_Previews",
    "tokens": [
      "atbottom",
      "attop",
      "bottom",
      "effect",
      "previews",
      "top"
    ],
    "members": [
      "ATBottomTopEffect_Previews",
      "ATTopBottomEffect_Previews"
    ]
  },
  {
    "size": 2,
    "rep": "Attribute",
    "tokens": [
      "attribute",
      "attributes"
    ],
    "members": [
      "Attribute",
      "Attributes"
    ]
  },
  {
    "size": 2,
    "rep": "Background",
    "tokens": [
      "background",
      "bckground"
    ],
    "members": [
      "Background",
      "Bckground"
    ]
  },
  {
    "size": 2,
    "rep": "Behavior",
    "tokens": [
      "behavior",
      "behaviour"
    ],
    "members": [
      "Behavior",
      "Behaviour"
    ]
  },
  {
    "size": 2,
    "rep": "BLEDevice",
    "tokens": [
      "ble",
      "bledevice",
      "device"
    ],
    "members": [
      "BLEDevice",
      "bleDevice"
    ]
  },
  {
    "size": 2,
    "rep": "Blinds_Preview",
    "tokens": [
      "blinds",
      "preview",
      "previews"
    ],
    "members": [
      "Blinds_Preview",
      "Blinds_Previews"
    ]
  },
  {
    "size": 2,
    "rep": "Blur_Preview",
    "tokens": [
      "blur",
      "preview",
      "previews"
    ],
    "members": [
      "Blur_Preview",
      "Blur_Previews"
    ]
  },
  {
    "size": 2,
    "rep": "Body",
    "tokens": [
      "body"
    ],
    "members": [
      "Body",
      "body"
    ]
  },
  {
    "size": 2,
    "rep": "Boing_2_Previews",
    "tokens": [
      "2",
      "boing",
      "preview",
      "previews"
    ],
    "members": [
      "Boing_2_Previews",
      "Boing_Preview"
    ]
  },
  {
    "size": 2,
    "rep": "Bookmark",
    "tokens": [
      "bookmark",
      "bookmarks"
    ],
    "members": [
      "Bookmark",
      "Bookmarks"
    ]
  },
  {
    "size": 2,
    "rep": "Border",
    "tokens": [
      "border",
      "borders"
    ],
    "members": [
      "Border",
      "Borders"
    ]
  },
  {
    "size": 2,
    "rep": "BuildSetting",
    "tokens": [
      "build",
      "setting",
      "settings"
    ],
    "members": [
      "BuildSetting",
      "BuildSettings"
    ]
  },
  {
    "size": 2,
    "rep": "ButtonView",
    "tokens": [
      "button",
      "buttons",
      "view"
    ],
    "members": [
      "ButtonView",
      "ButtonsView"
    ]
  },
  {
    "size": 2,
    "rep": "CardContainer",
    "tokens": [
      "card",
      "cards",
      "container"
    ],
    "members": [
      "CardContainer",
      "CardsContainer"
    ]
  },
  {
    "size": 2,
    "rep": "CareStoreFetchedResult",
    "tokens": [
      "care",
      "fetched",
      "result",
      "results",
      "store"
    ],
    "members": [
      "CareStoreFetchedResult",
      "CareStoreFetchedResults"
    ]
  },
  {
    "size": 2,
    "rep": "CaseStudyNavigationStack",
    "tokens": [
      "case",
      "mac",
      "navigation",
      "stack",
      "study"
    ],
    "members": [
      "CaseStudyNavigationStack",
      "CaseStudyNavigationStackMac"
    ]
  },
  {
    "size": 2,
    "rep": "CellStyle",
    "tokens": [
      "cell",
      "style",
      "styles"
    ],
    "members": [
      "CellStyle",
      "CellStyles"
    ]
  },
  {
    "size": 2,
    "rep": "ChaChaDecryptor",
    "tokens": [
      "cha",
      "decryptor",
      "encryptor"
    ],
    "members": [
      "ChaChaDecryptor",
      "ChaChaEncryptor"
    ]
  },
  {
    "size": 2,
    "rep": "Characteristic",
    "tokens": [
      "characteristic",
      "characteristics"
    ],
    "members": [
      "Characteristic",
      "Characteristics"
    ]
  },
  {
    "size": 2,
    "rep": "ChatView",
    "tokens": [
      "chat",
      "chats",
      "view"
    ],
    "members": [
      "ChatView",
      "ChatsView"
    ]
  },
  {
    "size": 2,
    "rep": "Circle",
    "tokens": [
      "circle",
      "circles"
    ],
    "members": [
      "Circle",
      "Circles"
    ]
  },
  {
    "size": 2,
    "rep": "Circle_Previews",
    "tokens": [
      "circle",
      "circles",
      "previews"
    ],
    "members": [
      "Circle_Previews",
      "Circles_Previews"
    ]
  },
  {
    "size": 2,
    "rep": "Clock_Preview",
    "tokens": [
      "clock",
      "preview",
      "previews"
    ],
    "members": [
      "Clock_Preview",
      "Clock_Previews"
    ]
  },
  {
    "size": 2,
    "rep": "Cogwheel",
    "tokens": [
      "cogwheel",
      "cogwheels"
    ],
    "members": [
      "Cogwheel",
      "Cogwheels"
    ]
  },
  {
    "size": 2,
    "rep": "CogwheelWithRotation_Previews",
    "tokens": [
      "cogwheel",
      "cogwheels",
      "previews",
      "rotation",
      "with"
    ],
    "members": [
      "CogwheelWithRotation_Previews",
      "CogwheelsWithRotation_Previews"
    ]
  },
  {
    "size": 2,
    "rep": "Column",
    "tokens": [
      "column",
      "columns"
    ],
    "members": [
      "Column",
      "Columns"
    ]
  },
  {
    "size": 2,
    "rep": "CombineLatest3AsyncSequence",
    "tokens": [
      "async",
      "combine",
      "latest",
      "latest3async",
      "sequence"
    ],
    "members": [
      "CombineLatest3AsyncSequence",
      "CombineLatestAsyncSequence"
    ]
  },
  {
    "size": 2,
    "rep": "Command",
    "tokens": [
      "command",
      "commands"
    ],
    "members": [
      "Command",
      "Commands"
    ]
  },
  {
    "size": 2,
    "rep": "Comment",
    "tokens": [
      "comment",
      "comments"
    ],
    "members": [
      "Comment",
      "Comments"
    ]
  },
  {
    "size": 2,
    "rep": "Compiler_Protobuf_ClassGetter",
    "tokens": [
      "class",
      "compiler",
      "getter",
      "protobuf",
      "setter"
    ],
    "members": [
      "Compiler_Protobuf_ClassGetter",
      "Compiler_Protobuf_ClassSetter"
    ]
  },
  {
    "size": 2,
    "rep": "Compiler_Protobuf_IfStatement",
    "tokens": [
      "compiler",
      "if",
      "protobuf",
      "statement"
    ],
    "members": [
      "Compiler_Protobuf_IfStatement",
      "Compiler_Protobuf_Statement"
    ]
  },
  {
    "size": 2,
    "rep": "Compiler_Protobuf_ObjectGetter",
    "tokens": [
      "compiler",
      "getter",
      "object",
      "protobuf",
      "setter"
    ],
    "members": [
      "Compiler_Protobuf_ObjectGetter",
      "Compiler_Protobuf_ObjectSetter"
    ]
  },
  {
    "size": 2,
    "rep": "Compiler_Protobuf_ThrowStatement",
    "tokens": [
      "compiler",
      "protobuf",
      "statement",
      "throw",
      "try"
    ],
    "members": [
      "Compiler_Protobuf_ThrowStatement",
      "Compiler_Protobuf_TryStatement"
    ]
  },
  {
    "size": 2,
    "rep": "Compiler_Protobuf_VariableDeclaration",
    "tokens": [
      "compiler",
      "declaration",
      "declarator",
      "protobuf",
      "variable"
    ],
    "members": [
      "Compiler_Protobuf_VariableDeclaration",
      "Compiler_Protobuf_VariableDeclarator"
    ]
  },
  {
    "size": 2,
    "rep": "Component",
    "tokens": [
      "component",
      "components"
    ],
    "members": [
      "Component",
      "Components"
    ]
  },
  {
    "size": 2,
    "rep": "Condition",
    "tokens": [
      "condition",
      "conditions"
    ],
    "members": [
      "Condition",
      "Conditions"
    ]
  },
  {
    "size": 2,
    "rep": "ConsoleSearchSuggestionView",
    "tokens": [
      "console",
      "search",
      "suggestion",
      "suggestions",
      "view"
    ],
    "members": [
      "ConsoleSearchSuggestionView",
      "ConsoleSearchSuggestionsView"
    ]
  },
  {
    "size": 2,
    "rep": "Constant",
    "tokens": [
      "constant",
      "constants"
    ],
    "members": [
      "Constant",
      "Constants"
    ]
  },
  {
    "size": 2,
    "rep": "ContactView",
    "tokens": [
      "contact",
      "contacts",
      "view"
    ],
    "members": [
      "ContactView",
      "ContactsView"
    ]
  },
  {
    "size": 2,
    "rep": "ContainerEnvironment",
    "tokens": [
      "container",
      "environment",
      "key"
    ],
    "members": [
      "ContainerEnvironment",
      "ContainerEnvironmentKey"
    ]
  },
  {
    "size": 2,
    "rep": "Content",
    "tokens": [
      "content"
    ],
    "members": [
      "Content",
      "content"
    ]
  },
  {
    "size": 2,
    "rep": "ContentMode",
    "tokens": [
      "content",
      "mode",
      "modes"
    ],
    "members": [
      "ContentMode",
      "ContentModes"
    ]
  },
  {
    "size": 2,
    "rep": "ContentViewPreviews",
    "tokens": [
      "content",
      "previews",
      "view"
    ],
    "members": [
      "ContentViewPreviews",
      "ContentView_Previews"
    ]
  },
  {
    "size": 2,
    "rep": "Contile",
    "tokens": [
      "contile",
      "contiles"
    ],
    "members": [
      "Contile",
      "Contiles"
    ]
  },
  {
    "size": 2,
    "rep": "ContributionCalendar",
    "tokens": [
      "calendar",
      "contribution",
      "day"
    ],
    "members": [
      "ContributionCalendar",
      "ContributionCalendarDay"
    ]
  },
  {
    "size": 2,
    "rep": "ControlView",
    "tokens": [
      "control",
      "controls",
      "view"
    ],
    "members": [
      "ControlView",
      "ControlsView"
    ]
  },
  {
    "size": 2,
    "rep": "CookieState",
    "tokens": [
      "cookie",
      "cookies",
      "state"
    ],
    "members": [
      "CookieState",
      "CookiesState"
    ]
  },
  {
    "size": 2,
    "rep": "CreateProjectInput",
    "tokens": [
      "create",
      "input",
      "project",
      "v2input"
    ],
    "members": [
      "CreateProjectInput",
      "CreateProjectV2Input"
    ]
  },
  {
    "size": 2,
    "rep": "CreateProjectPayload",
    "tokens": [
      "create",
      "payload",
      "project",
      "v2payload"
    ],
    "members": [
      "CreateProjectPayload",
      "CreateProjectV2Payload"
    ]
  },
  {
    "size": 2,
    "rep": "CreateSponsorshipInput",
    "tokens": [
      "create",
      "input",
      "sponsorship",
      "sponsorships"
    ],
    "members": [
      "CreateSponsorshipInput",
      "CreateSponsorshipsInput"
    ]
  },
  {
    "size": 2,
    "rep": "CreateSponsorshipPayload",
    "tokens": [
      "create",
      "payload",
      "sponsorship",
      "sponsorships"
    ],
    "members": [
      "CreateSponsorshipPayload",
      "CreateSponsorshipsPayload"
    ]
  },
  {
    "size": 2,
    "rep": "Credential",
    "tokens": [
      "credential",
      "credentials"
    ],
    "members": [
      "Credential",
      "Credentials"
    ]
  },
  {
    "size": 2,
    "rep": "CreditCard",
    "tokens": [
      "card",
      "cards",
      "credit"
    ],
    "members": [
      "CreditCard",
      "CreditCards"
    ]
  },
  {
    "size": 2,
    "rep": "DataType",
    "tokens": [
      "data",
      "type",
      "types"
    ],
    "members": [
      "DataType",
      "DataTypes"
    ]
  },
  {
    "size": 2,
    "rep": "DateFormat",
    "tokens": [
      "date",
      "format",
      "formats"
    ],
    "members": [
      "DateFormat",
      "DateFormats"
    ]
  },
  {
    "size": 2,
    "rep": "DateValue",
    "tokens": [
      "date",
      "value",
      "values"
    ],
    "members": [
      "DateValue",
      "DateValues"
    ]
  },
  {
    "size": 2,
    "rep": "Decode",
    "tokens": [
      "decode",
      "decoder"
    ],
    "members": [
      "Decode",
      "Decoder"
    ]
  },
  {
    "size": 2,
    "rep": "DefaultsKey",
    "tokens": [
      "defaults",
      "key",
      "keys"
    ],
    "members": [
      "DefaultsKey",
      "DefaultsKeys"
    ]
  },
  {
    "size": 2,
    "rep": "DeleteProjectInput",
    "tokens": [
      "delete",
      "input",
      "project",
      "v2input"
    ],
    "members": [
      "DeleteProjectInput",
      "DeleteProjectV2Input"
    ]
  },
  {
    "size": 2,
    "rep": "DeleteProjectPayload",
    "tokens": [
      "delete",
      "payload",
      "project",
      "v2payload"
    ],
    "members": [
      "DeleteProjectPayload",
      "DeleteProjectV2Payload"
    ]
  },
  {
    "size": 2,
    "rep": "DemoText2MessageContentFactory",
    "tokens": [
      "content",
      "demo",
      "factory",
      "message",
      "text",
      "text2message"
    ],
    "members": [
      "DemoText2MessageContentFactory",
      "DemoTextMessageContentFactory"
    ]
  },
  {
    "size": 2,
    "rep": "DeploymentReview",
    "tokens": [
      "deployment",
      "review",
      "reviewer"
    ],
    "members": [
      "DeploymentReview",
      "DeploymentReviewer"
    ]
  },
  {
    "size": 2,
    "rep": "DeploymentReviewConnection",
    "tokens": [
      "connection",
      "deployment",
      "review",
      "reviewer"
    ],
    "members": [
      "DeploymentReviewConnection",
      "DeploymentReviewerConnection"
    ]
  },
  {
    "size": 2,
    "rep": "DividedHStackLayout",
    "tokens": [
      "divided",
      "hstack",
      "layout",
      "vstack"
    ],
    "members": [
      "DividedHStackLayout",
      "DividedVStackLayout"
    ]
  },
  {
    "size": 2,
    "rep": "Download",
    "tokens": [
      "download",
      "downloads"
    ],
    "members": [
      "Download",
      "Downloads"
    ]
  },
  {
    "size": 2,
    "rep": "DrawnIndicator",
    "tokens": [
      "drawn",
      "indicator",
      "indicators"
    ],
    "members": [
      "DrawnIndicator",
      "DrawnIndicators"
    ]
  },
  {
    "size": 2,
    "rep": "EaseInOutExample",
    "tokens": [
      "ease",
      "example",
      "in",
      "out"
    ],
    "members": [
      "EaseInOutExample",
      "EaseOutExample"
    ]
  },
  {
    "size": 2,
    "rep": "Element",
    "tokens": [
      "element",
      "elements"
    ],
    "members": [
      "Element",
      "Elements"
    ]
  },
  {
    "size": 2,
    "rep": "EmptyLifeGoalsCompletedList",
    "tokens": [
      "completed",
      "empty",
      "goals",
      "life",
      "list",
      "uncompleted"
    ],
    "members": [
      "EmptyLifeGoalsCompletedList",
      "EmptyLifeGoalsUncompletedList"
    ]
  },
  {
    "size": 2,
    "rep": "Environment",
    "tokens": [
      "environment",
      "environments"
    ],
    "members": [
      "Environment",
      "Environments"
    ]
  },
  {
    "size": 2,
    "rep": "EnvironmentInsertions",
    "tokens": [
      "environment",
      "insertions",
      "key"
    ],
    "members": [
      "EnvironmentInsertions",
      "EnvironmentInsertionsKey"
    ]
  },
  {
    "size": 2,
    "rep": "EnvironmentKey",
    "tokens": [
      "environment",
      "key",
      "keys"
    ],
    "members": [
      "EnvironmentKey",
      "EnvironmentKeys"
    ]
  },
  {
    "size": 2,
    "rep": "EnvironmentValue",
    "tokens": [
      "environment",
      "value",
      "values"
    ],
    "members": [
      "EnvironmentValue",
      "EnvironmentValues"
    ]
  },
  {
    "size": 2,
    "rep": "EpoxyIntrinsicContentSizeInvalidator",
    "tokens": [
      "content",
      "epoxy",
      "intrinsic",
      "invalidator",
      "key",
      "size"
    ],
    "members": [
      "EpoxyIntrinsicContentSizeInvalidator",
      "EpoxyIntrinsicContentSizeInvalidatorKey"
    ]
  },
  {
    "size": 2,
    "rep": "Example",
    "tokens": [
      "example",
      "examples"
    ],
    "members": [
      "Example",
      "Examples"
    ]
  },
  {
    "size": 2,
    "rep": "Expression",
    "tokens": [
      "expression",
      "expressions"
    ],
    "members": [
      "Expression",
      "Expressions"
    ]
  },
  {
    "size": 2,
    "rep": "Extension",
    "tokens": [
      "extension",
      "extensions"
    ],
    "members": [
      "Extension",
      "Extensions"
    ]
  },
  {
    "size": 2,
    "rep": "FeatureFlags",
    "tokens": [
      "feature",
      "flags",
      "ui"
    ],
    "members": [
      "FeatureFlags",
      "FeatureFlagsUI"
    ]
  },
  {
    "size": 2,
    "rep": "FeatureModel",
    "tokens": [
      "feature",
      "features",
      "model"
    ],
    "members": [
      "FeatureModel",
      "FeaturesModel"
    ]
  },
  {
    "size": 2,
    "rep": "FileChunkIterator",
    "tokens": [
      "chunk",
      "chunks",
      "file",
      "iterator"
    ],
    "members": [
      "FileChunkIterator",
      "FileChunksIterator"
    ]
  },
  {
    "size": 2,
    "rep": "FileError",
    "tokens": [
      "error",
      "file",
      "files"
    ],
    "members": [
      "FileError",
      "FilesError"
    ]
  },
  {
    "size": 2,
    "rep": "FileHelper",
    "tokens": [
      "file",
      "helper",
      "helpers"
    ],
    "members": [
      "FileHelper",
      "FileHelpers"
    ]
  },
  {
    "size": 2,
    "rep": "FileType",
    "tokens": [
      "file",
      "type",
      "types"
    ],
    "members": [
      "FileType",
      "FileTypes"
    ]
  },
  {
    "size": 2,
    "rep": "FileUtil",
    "tokens": [
      "file",
      "util",
      "utils"
    ],
    "members": [
      "FileUtil",
      "FileUtils"
    ]
  },
  {
    "size": 2,
    "rep": "FilterView",
    "tokens": [
      "filter",
      "filters",
      "view"
    ],
    "members": [
      "FilterView",
      "FiltersView"
    ]
  },
  {
    "size": 2,
    "rep": "Flicker_Preview",
    "tokens": [
      "flicker",
      "preview",
      "previews"
    ],
    "members": [
      "Flicker_Preview",
      "Flicker_Previews"
    ]
  },
  {
    "size": 2,
    "rep": "Function",
    "tokens": [
      "function",
      "functions"
    ],
    "members": [
      "Function",
      "Functions"
    ]
  },
  {
    "size": 2,
    "rep": "Fuzzilli_Protobuf_BeginClassConstructor",
    "tokens": [
      "begin",
      "class",
      "constructor",
      "end",
      "fuzzilli",
      "protobuf"
    ],
    "members": [
      "Fuzzilli_Protobuf_BeginClassConstructor",
      "Fuzzilli_Protobuf_EndClassConstructor"
    ]
  },
  {
    "size": 2,
    "rep": "Fuzzilli_Protobuf_BeginClassStaticGetter",
    "tokens": [
      "begin",
      "class",
      "fuzzilli",
      "getter",
      "protobuf",
      "setter",
      "static"
    ],
    "members": [
      "Fuzzilli_Protobuf_BeginClassStaticGetter",
      "Fuzzilli_Protobuf_BeginClassStaticSetter"
    ]
  },
  {
    "size": 2,
    "rep": "Fuzzilli_Protobuf_BeginConstructor",
    "tokens": [
      "begin",
      "constructor",
      "end",
      "fuzzilli",
      "protobuf"
    ],
    "members": [
      "Fuzzilli_Protobuf_BeginConstructor",
      "Fuzzilli_Protobuf_EndConstructor"
    ]
  },
  {
    "size": 2,
    "rep": "Fuzzilli_Protobuf_BeginRepeatLoop",
    "tokens": [
      "begin",
      "end",
      "fuzzilli",
      "loop",
      "protobuf",
      "repeat"
    ],
    "members": [
      "Fuzzilli_Protobuf_BeginRepeatLoop",
      "Fuzzilli_Protobuf_EndRepeatLoop"
    ]
  },
  {
    "size": 2,
    "rep": "Fuzzilli_Protobuf_BeginSwitch",
    "tokens": [
      "begin",
      "fuzzilli",
      "protobuf",
      "switch",
      "with"
    ],
    "members": [
      "Fuzzilli_Protobuf_BeginSwitch",
      "Fuzzilli_Protobuf_BeginWith"
    ]
  },
  {
    "size": 2,
    "rep": "Fuzzilli_Protobuf_Constf32",
    "tokens": [
      "constf32",
      "consti32",
      "fuzzilli",
      "protobuf"
    ],
    "members": [
      "Fuzzilli_Protobuf_Constf32",
      "Fuzzilli_Protobuf_Consti32"
    ]
  },
  {
    "size": 2,
    "rep": "Fuzzilli_Protobuf_Constf64",
    "tokens": [
      "constf64",
      "consti64",
      "fuzzilli",
      "protobuf"
    ],
    "members": [
      "Fuzzilli_Protobuf_Constf64",
      "Fuzzilli_Protobuf_Consti64"
    ]
  },
  {
    "size": 2,
    "rep": "Fuzzilli_Protobuf_CreateArray",
    "tokens": [
      "array",
      "create",
      "fuzzilli",
      "int",
      "protobuf"
    ],
    "members": [
      "Fuzzilli_Protobuf_CreateArray",
      "Fuzzilli_Protobuf_CreateIntArray"
    ]
  },
  {
    "size": 2,
    "rep": "Fuzzilli_Protobuf_EndClassInstanceGetter",
    "tokens": [
      "class",
      "end",
      "fuzzilli",
      "getter",
      "instance",
      "protobuf",
      "setter"
    ],
    "members": [
      "Fuzzilli_Protobuf_EndClassInstanceGetter",
      "Fuzzilli_Protobuf_EndClassInstanceSetter"
    ]
  },
  {
    "size": 2,
    "rep": "Fuzzilli_Protobuf_EndClassStaticGetter",
    "tokens": [
      "class",
      "end",
      "fuzzilli",
      "getter",
      "protobuf",
      "setter",
      "static"
    ],
    "members": [
      "Fuzzilli_Protobuf_EndClassStaticGetter",
      "Fuzzilli_Protobuf_EndClassStaticSetter"
    ]
  },
  {
    "size": 2,
    "rep": "Fuzzilli_Protobuf_EndObjectLiteralGetter",
    "tokens": [
      "end",
      "fuzzilli",
      "getter",
      "literal",
      "object",
      "protobuf",
      "setter"
    ],
    "members": [
      "Fuzzilli_Protobuf_EndObjectLiteralGetter",
      "Fuzzilli_Protobuf_EndObjectLiteralSetter"
    ]
  },
  {
    "size": 2,
    "rep": "Fuzzilli_Protobuf_EndSwitch",
    "tokens": [
      "end",
      "fuzzilli",
      "protobuf",
      "switch",
      "with"
    ],
    "members": [
      "Fuzzilli_Protobuf_EndSwitch",
      "Fuzzilli_Protobuf_EndWith"
    ]
  },
  {
    "size": 2,
    "rep": "Fuzzilli_Protobuf_GetComputedProperty",
    "tokens": [
      "computed",
      "fuzzilli",
      "get",
      "property",
      "protobuf",
      "set"
    ],
    "members": [
      "Fuzzilli_Protobuf_GetComputedProperty",
      "Fuzzilli_Protobuf_SetComputedProperty"
    ]
  },
  {
    "size": 2,
    "rep": "Fuzzilli_Protobuf_GetElement",
    "tokens": [
      "element",
      "fuzzilli",
      "get",
      "protobuf",
      "set"
    ],
    "members": [
      "Fuzzilli_Protobuf_GetElement",
      "Fuzzilli_Protobuf_SetElement"
    ]
  },
  {
    "size": 2,
    "rep": "Fuzzilli_Protobuf_GetPrivateProperty",
    "tokens": [
      "fuzzilli",
      "get",
      "private",
      "property",
      "protobuf",
      "set"
    ],
    "members": [
      "Fuzzilli_Protobuf_GetPrivateProperty",
      "Fuzzilli_Protobuf_SetPrivateProperty"
    ]
  },
  {
    "size": 2,
    "rep": "Fuzzilli_Protobuf_GetProperty",
    "tokens": [
      "fuzzilli",
      "get",
      "property",
      "protobuf",
      "set"
    ],
    "members": [
      "Fuzzilli_Protobuf_GetProperty",
      "Fuzzilli_Protobuf_SetProperty"
    ]
  },
  {
    "size": 2,
    "rep": "Fuzzilli_Protobuf_GetSuperProperty",
    "tokens": [
      "fuzzilli",
      "get",
      "property",
      "protobuf",
      "set",
      "super"
    ],
    "members": [
      "Fuzzilli_Protobuf_GetSuperProperty",
      "Fuzzilli_Protobuf_SetSuperProperty"
    ]
  },
  {
    "size": 2,
    "rep": "Fuzzilli_Protobuf_WasmBeginCatch",
    "tokens": [
      "all",
      "begin",
      "catch",
      "fuzzilli",
      "protobuf",
      "wasm"
    ],
    "members": [
      "Fuzzilli_Protobuf_WasmBeginCatch",
      "Fuzzilli_Protobuf_WasmBeginCatchAll"
    ]
  },
  {
    "size": 2,
    "rep": "Fuzzilli_Protobuf_WasmBeginLoop",
    "tokens": [
      "begin",
      "end",
      "fuzzilli",
      "loop",
      "protobuf",
      "wasm"
    ],
    "members": [
      "Fuzzilli_Protobuf_WasmBeginLoop",
      "Fuzzilli_Protobuf_WasmEndLoop"
    ]
  },
  {
    "size": 2,
    "rep": "Fuzzilli_Protobuf_WasmBeginTry",
    "tokens": [
      "begin",
      "end",
      "fuzzilli",
      "protobuf",
      "try",
      "wasm"
    ],
    "members": [
      "Fuzzilli_Protobuf_WasmBeginTry",
      "Fuzzilli_Protobuf_WasmEndTry"
    ]
  },
  {
    "size": 2,
    "rep": "Fuzzilli_Protobuf_WasmBranch",
    "tokens": [
      "branch",
      "fuzzilli",
      "if",
      "protobuf",
      "wasm"
    ],
    "members": [
      "Fuzzilli_Protobuf_WasmBranch",
      "Fuzzilli_Protobuf_WasmBranchIf"
    ]
  },
  {
    "size": 2,
    "rep": "Fuzzilli_Protobuf_WasmDefineTable",
    "tokens": [
      "define",
      "fuzzilli",
      "protobuf",
      "table",
      "tag",
      "wasm"
    ],
    "members": [
      "Fuzzilli_Protobuf_WasmDefineTable",
      "Fuzzilli_Protobuf_WasmDefineTag"
    ]
  },
  {
    "size": 2,
    "rep": "Fuzzilli_Protobuf_Wasmi32EqualZero",
    "tokens": [
      "fuzzilli",
      "protobuf",
      "wasmi32equal",
      "wasmi64equal",
      "zero"
    ],
    "members": [
      "Fuzzilli_Protobuf_Wasmi32EqualZero",
      "Fuzzilli_Protobuf_Wasmi64EqualZero"
    ]
  },
  {
    "size": 2,
    "rep": "Fuzzilli_Protobuf_WasmRethrow",
    "tokens": [
      "fuzzilli",
      "protobuf",
      "rethrow",
      "throw",
      "wasm"
    ],
    "members": [
      "Fuzzilli_Protobuf_WasmRethrow",
      "Fuzzilli_Protobuf_WasmThrow"
    ]
  },
  {
    "size": 2,
    "rep": "Fuzzilli_Protobuf_WasmSignExtend8Intoi32",
    "tokens": [
      "extend8intoi32",
      "extend8intoi64",
      "fuzzilli",
      "protobuf",
      "sign",
      "wasm"
    ],
    "members": [
      "Fuzzilli_Protobuf_WasmSignExtend8Intoi32",
      "Fuzzilli_Protobuf_WasmSignExtend8Intoi64"
    ]
  },
  {
    "size": 2,
    "rep": "Fuzzilli_Protobuf_WasmSimd128FloatBinOp",
    "tokens": [
      "bin",
      "fuzzilli",
      "op",
      "protobuf",
      "simd128float",
      "un",
      "wasm"
    ],
    "members": [
      "Fuzzilli_Protobuf_WasmSimd128FloatBinOp",
      "Fuzzilli_Protobuf_WasmSimd128FloatUnOp"
    ]
  },
  {
    "size": 2,
    "rep": "Fuzzilli_Protobuf_WasmTableGet",
    "tokens": [
      "fuzzilli",
      "get",
      "protobuf",
      "set",
      "table",
      "wasm"
    ],
    "members": [
      "Fuzzilli_Protobuf_WasmTableGet",
      "Fuzzilli_Protobuf_WasmTableSet"
    ]
  },
  {
    "size": 2,
    "rep": "GameScore",
    "tokens": [
      "game",
      "score",
      "score2"
    ],
    "members": [
      "GameScore",
      "GameScore2"
    ]
  },
  {
    "size": 2,
    "rep": "GeneralSettingsPage",
    "tokens": [
      "general",
      "page",
      "pane",
      "settings"
    ],
    "members": [
      "GeneralSettingsPage",
      "GeneralSettingsPane"
    ]
  },
  {
    "size": 2,
    "rep": "GeneralSettingView",
    "tokens": [
      "general",
      "setting",
      "settings",
      "view"
    ],
    "members": [
      "GeneralSettingView",
      "GeneralSettingsView"
    ]
  },
  {
    "size": 2,
    "rep": "GeneralTabView_Previews",
    "tokens": [
      "general",
      "previews",
      "tab",
      "view"
    ],
    "members": [
      "GeneralTabView_Previews",
      "GeneralView_Previews"
    ]
  },
  {
    "size": 2,
    "rep": "GenericCodingKey",
    "tokens": [
      "coding",
      "generic",
      "key",
      "keys"
    ],
    "members": [
      "GenericCodingKey",
      "GenericCodingKeys"
    ]
  },
  {
    "size": 2,
    "rep": "GetConfirmedBlock",
    "tokens": [
      "block",
      "blocks",
      "confirmed",
      "get"
    ],
    "members": [
      "GetConfirmedBlock",
      "GetConfirmedBlocks"
    ]
  },
  {
    "size": 2,
    "rep": "GetPlatformApplicationAttributesInput",
    "tokens": [
      "application",
      "attributes",
      "get",
      "input",
      "platform",
      "set"
    ],
    "members": [
      "GetPlatformApplicationAttributesInput",
      "SetPlatformApplicationAttributesInput"
    ]
  },
  {
    "size": 2,
    "rep": "Glare_Preview",
    "tokens": [
      "glare",
      "preview",
      "previews"
    ],
    "members": [
      "Glare_Preview",
      "Glare_Previews"
    ]
  },
  {
    "size": 2,
    "rep": "GridBackgroundPreference",
    "tokens": [
      "background",
      "grid",
      "key",
      "preference"
    ],
    "members": [
      "GridBackgroundPreference",
      "GridBackgroundPreferenceKey"
    ]
  },
  {
    "size": 2,
    "rep": "GridOverlayPreference",
    "tokens": [
      "grid",
      "key",
      "overlay",
      "preference"
    ],
    "members": [
      "GridOverlayPreference",
      "GridOverlayPreferenceKey"
    ]
  },
  {
    "size": 2,
    "rep": "HashableValue",
    "tokens": [
      "hashable",
      "value",
      "values"
    ],
    "members": [
      "HashableValue",
      "HashableValues"
    ]
  },
  {
    "size": 2,
    "rep": "Header",
    "tokens": [
      "header",
      "headers"
    ],
    "members": [
      "Header",
      "Headers"
    ]
  },
  {
    "size": 2,
    "rep": "HTTPHeader",
    "tokens": [
      "httpheader",
      "httpheaders"
    ],
    "members": [
      "HTTPHeader",
      "HTTPHeaders"
    ]
  },
  {
    "size": 2,
    "rep": "IdentifiedListSection",
    "tokens": [
      "identified",
      "list",
      "section",
      "sections"
    ],
    "members": [
      "IdentifiedListSection",
      "IdentifiedListSections"
    ]
  },
  {
    "size": 2,
    "rep": "Identifier",
    "tokens": [
      "identifier",
      "identifiers"
    ],
    "members": [
      "Identifier",
      "Identifiers"
    ]
  },
  {
    "size": 2,
    "rep": "ImageContainer",
    "tokens": [
      "container",
      "image",
      "images"
    ],
    "members": [
      "ImageContainer",
      "ImagesContainer"
    ]
  },
  {
    "size": 2,
    "rep": "IndicatorView",
    "tokens": [
      "indicator",
      "indicators",
      "view"
    ],
    "members": [
      "IndicatorView",
      "IndicatorsView"
    ]
  },
  {
    "size": 2,
    "rep": "InputFieldView",
    "tokens": [
      "field",
      "fields",
      "input",
      "view"
    ],
    "members": [
      "InputFieldView",
      "InputFieldsView"
    ]
  },
  {
    "size": 2,
    "rep": "InstanceVariable",
    "tokens": [
      "instance",
      "variable",
      "variables"
    ],
    "members": [
      "InstanceVariable",
      "InstanceVariables"
    ]
  },
  {
    "size": 2,
    "rep": "Interface",
    "tokens": [
      "interface",
      "interfaces"
    ],
    "members": [
      "Interface",
      "Interfaces"
    ]
  },
  {
    "size": 2,
    "rep": "InterfaceView",
    "tokens": [
      "interface",
      "interfaces",
      "view"
    ],
    "members": [
      "InterfaceView",
      "InterfacesView"
    ]
  },
  {
    "size": 2,
    "rep": "Internal",
    "tokens": [
      "internal",
      "internals"
    ],
    "members": [
      "Internal",
      "Internals"
    ]
  },
  {
    "size": 2,
    "rep": "InterspersedMapSequence",
    "tokens": [
      "interspersed",
      "map",
      "sequence"
    ],
    "members": [
      "InterspersedMapSequence",
      "InterspersedSequence"
    ]
  },
  {
    "size": 2,
    "rep": "Interval",
    "tokens": [
      "interval",
      "intervals"
    ],
    "members": [
      "Interval",
      "Intervals"
    ]
  },
  {
    "size": 2,
    "rep": "IssueTimelineItem",
    "tokens": [
      "issue",
      "item",
      "items",
      "timeline"
    ],
    "members": [
      "IssueTimelineItem",
      "IssueTimelineItems"
    ]
  },
  {
    "size": 2,
    "rep": "IssueTimelineItemEdge",
    "tokens": [
      "edge",
      "issue",
      "item",
      "items",
      "timeline"
    ],
    "members": [
      "IssueTimelineItemEdge",
      "IssueTimelineItemsEdge"
    ]
  },
  {
    "size": 2,
    "rep": "ITunesResponse",
    "tokens": [
      "i",
      "itunes",
      "response",
      "tunes"
    ],
    "members": [
      "ITunesResponse",
      "iTunesResponse"
    ]
  },
  {
    "size": 2,
    "rep": "JSON",
    "tokens": [
      "json"
    ],
    "members": [
      "JSON",
      "Json"
    ]
  },
  {
    "size": 2,
    "rep": "KeyboardShortcut",
    "tokens": [
      "keyboard",
      "shortcut",
      "shortcuts"
    ],
    "members": [
      "KeyboardShortcut",
      "KeyboardShortcuts"
    ]
  },
  {
    "size": 2,
    "rep": "KeyboardShortcutView",
    "tokens": [
      "keyboard",
      "shortcut",
      "shortcuts",
      "view"
    ],
    "members": [
      "KeyboardShortcutView",
      "KeyboardShortcutsView"
    ]
  },
  {
    "size": 2,
    "rep": "KeyCode",
    "tokens": [
      "code",
      "key",
      "keycode"
    ],
    "members": [
      "KeyCode",
      "Keycode"
    ]
  },
  {
    "size": 2,
    "rep": "LaunchEnvironment",
    "tokens": [
      "environment",
      "environments",
      "launch"
    ],
    "members": [
      "LaunchEnvironment",
      "LaunchEnvironments"
    ]
  },
  {
    "size": 2,
    "rep": "Layout",
    "tokens": [
      "layout"
    ],
    "members": [
      "Layout",
      "layout"
    ]
  },
  {
    "size": 2,
    "rep": "LazyCollectionView",
    "tokens": [
      "app",
      "collection",
      "lazy",
      "view"
    ],
    "members": [
      "LazyCollectionView",
      "LazyCollectionViewApp"
    ]
  },
  {
    "size": 2,
    "rep": "LegacyColor",
    "tokens": [
      "color",
      "colors",
      "legacy"
    ],
    "members": [
      "LegacyColor",
      "LegacyColors"
    ]
  },
  {
    "size": 2,
    "rep": "License",
    "tokens": [
      "license",
      "licenses"
    ],
    "members": [
      "License",
      "Licenses"
    ]
  },
  {
    "size": 2,
    "rep": "LicenseList",
    "tokens": [
      "license",
      "list",
      "plist"
    ],
    "members": [
      "LicenseList",
      "LicensePlist"
    ]
  },
  {
    "size": 2,
    "rep": "LinkViewPreview",
    "tokens": [
      "link",
      "preview",
      "previews",
      "view"
    ],
    "members": [
      "LinkViewPreview",
      "LinkView_Previews"
    ]
  },
  {
    "size": 2,
    "rep": "LogRecord",
    "tokens": [
      "log",
      "logrecord",
      "record"
    ],
    "members": [
      "LogRecord",
      "Logrecord"
    ]
  },
  {
    "size": 2,
    "rep": "MapPin",
    "tokens": [
      "map",
      "mapping",
      "pin"
    ],
    "members": [
      "MapPin",
      "Mapping"
    ]
  },
  {
    "size": 2,
    "rep": "MarkKeyedDecoding",
    "tokens": [
      "decoding",
      "keyed",
      "mark",
      "unkeyed"
    ],
    "members": [
      "MarkKeyedDecoding",
      "MarkUnkeyedDecoding"
    ]
  },
  {
    "size": 2,
    "rep": "MenuBarAppearanceConfigurationV1",
    "tokens": [
      "appearance",
      "bar",
      "configuration",
      "menu",
      "v1",
      "v2"
    ],
    "members": [
      "MenuBarAppearanceConfigurationV1",
      "MenuBarAppearanceConfigurationV2"
    ]
  },
  {
    "size": 2,
    "rep": "Merge3AsyncSequence",
    "tokens": [
      "async",
      "merge",
      "merge3async",
      "sequence"
    ],
    "members": [
      "Merge3AsyncSequence",
      "MergeAsyncSequence"
    ]
  },
  {
    "size": 2,
    "rep": "MergeCell",
    "tokens": [
      "cell",
      "cells",
      "merge"
    ],
    "members": [
      "MergeCell",
      "MergeCells"
    ]
  },
  {
    "size": 2,
    "rep": "Message",
    "tokens": [
      "message",
      "messages"
    ],
    "members": [
      "Message",
      "Messages"
    ]
  },
  {
    "size": 2,
    "rep": "MessageThreadEnvelope",
    "tokens": [
      "envelope",
      "message",
      "thread",
      "threads"
    ],
    "members": [
      "MessageThreadEnvelope",
      "MessageThreadsEnvelope"
    ]
  },
  {
    "size": 2,
    "rep": "Method",
    "tokens": [
      "method",
      "methods"
    ],
    "members": [
      "Method",
      "Methods"
    ]
  },
  {
    "size": 2,
    "rep": "MIMEType",
    "tokens": [
      "mime",
      "mimetype",
      "type"
    ],
    "members": [
      "MIMEType",
      "MimeType"
    ]
  },
  {
    "size": 2,
    "rep": "ModeInfo",
    "tokens": [
      "info",
      "mode",
      "model"
    ],
    "members": [
      "ModeInfo",
      "ModelInfo"
    ]
  },
  {
    "size": 2,
    "rep": "Modifier",
    "tokens": [
      "modifier",
      "modifiers"
    ],
    "members": [
      "Modifier",
      "Modifiers"
    ]
  },
  {
    "size": 2,
    "rep": "NavigationDestination",
    "tokens": [
      "destination",
      "id",
      "navigation"
    ],
    "members": [
      "NavigationDestination",
      "NavigationDestinationID"
    ]
  },
  {
    "size": 2,
    "rep": "NewsletterSubscription",
    "tokens": [
      "newsletter",
      "subscription",
      "subscriptions"
    ],
    "members": [
      "NewsletterSubscription",
      "NewsletterSubscriptions"
    ]
  },
  {
    "size": 2,
    "rep": "Notification",
    "tokens": [
      "notification",
      "notifications"
    ],
    "members": [
      "Notification",
      "Notifications"
    ]
  },
  {
    "size": 2,
    "rep": "NotificationView",
    "tokens": [
      "notification",
      "notifications",
      "view"
    ],
    "members": [
      "NotificationView",
      "NotificationsView"
    ]
  },
  {
    "size": 2,
    "rep": "NumberFormat",
    "tokens": [
      "format",
      "formats",
      "number"
    ],
    "members": [
      "NumberFormat",
      "NumberFormats"
    ]
  },
  {
    "size": 2,
    "rep": "ObservableState",
    "tokens": [
      "id",
      "observable",
      "state"
    ],
    "members": [
      "ObservableState",
      "ObservableStateID"
    ]
  },
  {
    "size": 2,
    "rep": "OnboardingButton",
    "tokens": [
      "button",
      "buttons",
      "onboarding"
    ],
    "members": [
      "OnboardingButton",
      "OnboardingButtons"
    ]
  },
  {
    "size": 2,
    "rep": "OnFirstAppear",
    "tokens": [
      "appear",
      "first",
      "id",
      "on"
    ],
    "members": [
      "OnFirstAppear",
      "OnFirstAppearID"
    ]
  },
  {
    "size": 2,
    "rep": "Option",
    "tokens": [
      "option",
      "options"
    ],
    "members": [
      "Option",
      "Options"
    ]
  },
  {
    "size": 2,
    "rep": "OWWeather",
    "tokens": [
      "oweather",
      "owweather"
    ],
    "members": [
      "OWWeather",
      "OWeather"
    ]
  },
  {
    "size": 2,
    "rep": "PageView",
    "tokens": [
      "page",
      "pager",
      "view"
    ],
    "members": [
      "PageView",
      "PagerView"
    ]
  },
  {
    "size": 2,
    "rep": "Parameter",
    "tokens": [
      "parameter",
      "parameters"
    ],
    "members": [
      "Parameter",
      "Parameters"
    ]
  },
  {
    "size": 2,
    "rep": "ParseFile",
    "tokens": [
      "file",
      "parse",
      "parsed"
    ],
    "members": [
      "ParseFile",
      "ParsedFile"
    ]
  },
  {
    "size": 2,
    "rep": "Parser",
    "tokens": [
      "parser",
      "parsers"
    ],
    "members": [
      "Parser",
      "Parsers"
    ]
  },
  {
    "size": 2,
    "rep": "Password",
    "tokens": [
      "password",
      "passwords"
    ],
    "members": [
      "Password",
      "Passwords"
    ]
  },
  {
    "size": 2,
    "rep": "Placeholder",
    "tokens": [
      "placeholder",
      "placeholders"
    ],
    "members": [
      "Placeholder",
      "Placeholders"
    ]
  },
  {
    "size": 2,
    "rep": "Platform",
    "tokens": [
      "platform",
      "platforms"
    ],
    "members": [
      "Platform",
      "Platforms"
    ]
  },
  {
    "size": 2,
    "rep": "Pledge",
    "tokens": [
      "pledge",
      "pledged"
    ],
    "members": [
      "Pledge",
      "Pledged"
    ]
  },
  {
    "size": 2,
    "rep": "PointTrackConfiguration",
    "tokens": [
      "configuration",
      "key",
      "point",
      "track"
    ],
    "members": [
      "PointTrackConfiguration",
      "PointTrackConfigurationKey"
    ]
  },
  {
    "size": 2,
    "rep": "Pop_Preview",
    "tokens": [
      "pop",
      "preview",
      "previews"
    ],
    "members": [
      "Pop_Preview",
      "Pop_Previews"
    ]
  },
  {
    "size": 2,
    "rep": "PreferencesViewPreview",
    "tokens": [
      "preferences",
      "preview",
      "previews",
      "view"
    ],
    "members": [
      "PreferencesViewPreview",
      "PreferencesView_Previews"
    ]
  },
  {
    "size": 2,
    "rep": "Presentation",
    "tokens": [
      "id",
      "presentation"
    ],
    "members": [
      "Presentation",
      "PresentationID"
    ]
  },
  {
    "size": 2,
    "rep": "PreviewView",
    "tokens": [
      "preview",
      "previews",
      "view"
    ],
    "members": [
      "PreviewView",
      "PreviewsView"
    ]
  },
  {
    "size": 2,
    "rep": "Profile",
    "tokens": [
      "profile"
    ],
    "members": [
      "Profile",
      "profile"
    ]
  },
  {
    "size": 2,
    "rep": "ProjectConnection",
    "tokens": [
      "connection",
      "project",
      "v2connection"
    ],
    "members": [
      "ProjectConnection",
      "ProjectV2Connection"
    ]
  },
  {
    "size": 2,
    "rep": "ProjectOrder",
    "tokens": [
      "order",
      "project",
      "v2order"
    ],
    "members": [
      "ProjectOrder",
      "ProjectV2Order"
    ]
  },
  {
    "size": 2,
    "rep": "ProjectOwner",
    "tokens": [
      "owner",
      "project",
      "v2owner"
    ],
    "members": [
      "ProjectOwner",
      "ProjectV2Owner"
    ]
  },
  {
    "size": 2,
    "rep": "ProjectV2ItemFieldNumberValue",
    "tokens": [
      "field",
      "number",
      "project",
      "user",
      "v2item",
      "value"
    ],
    "members": [
      "ProjectV2ItemFieldNumberValue",
      "ProjectV2ItemFieldUserValue"
    ]
  },
  {
    "size": 2,
    "rep": "Protocol",
    "tokens": [
      "protocol",
      "protocols"
    ],
    "members": [
      "Protocol",
      "Protocols"
    ]
  },
  {
    "size": 2,
    "rep": "PullRequestTimelineItem",
    "tokens": [
      "item",
      "items",
      "pull",
      "request",
      "timeline"
    ],
    "members": [
      "PullRequestTimelineItem",
      "PullRequestTimelineItems"
    ]
  },
  {
    "size": 2,
    "rep": "PullRequestTimelineItemEdge",
    "tokens": [
      "edge",
      "item",
      "items",
      "pull",
      "request",
      "timeline"
    ],
    "members": [
      "PullRequestTimelineItemEdge",
      "PullRequestTimelineItemsEdge"
    ]
  },
  {
    "size": 2,
    "rep": "RangeTrackConfiguration",
    "tokens": [
      "configuration",
      "key",
      "range",
      "track"
    ],
    "members": [
      "RangeTrackConfiguration",
      "RangeTrackConfigurationKey"
    ]
  },
  {
    "size": 2,
    "rep": "Rectangle",
    "tokens": [
      "rectangle",
      "rectangles"
    ],
    "members": [
      "Rectangle",
      "Rectangles"
    ]
  },
  {
    "size": 2,
    "rep": "Reduce",
    "tokens": [
      "reduce",
      "reduced"
    ],
    "members": [
      "Reduce",
      "Reduced"
    ]
  },
  {
    "size": 2,
    "rep": "Register",
    "tokens": [
      "register",
      "registers"
    ],
    "members": [
      "Register",
      "Registers"
    ]
  },
  {
    "size": 2,
    "rep": "Relationship",
    "tokens": [
      "relationship",
      "relationships"
    ],
    "members": [
      "Relationship",
      "Relationships"
    ]
  },
  {
    "size": 2,
    "rep": "ResolvedPackagesV1",
    "tokens": [
      "packages",
      "resolved",
      "v1",
      "v2"
    ],
    "members": [
      "ResolvedPackagesV1",
      "ResolvedPackagesV2"
    ]
  },
  {
    "size": 2,
    "rep": "Resource",
    "tokens": [
      "resource",
      "resources"
    ],
    "members": [
      "Resource",
      "Resources"
    ]
  },
  {
    "size": 2,
    "rep": "ResultView",
    "tokens": [
      "result",
      "results",
      "view"
    ],
    "members": [
      "ResultView",
      "ResultsView"
    ]
  },
  {
    "size": 2,
    "rep": "RoundedCorner",
    "tokens": [
      "corner",
      "corners",
      "rounded"
    ],
    "members": [
      "RoundedCorner",
      "RoundedCorners"
    ]
  },
  {
    "size": 2,
    "rep": "RuleParameter",
    "tokens": [
      "parameter",
      "parameters",
      "rule"
    ],
    "members": [
      "RuleParameter",
      "RuleParameters"
    ]
  },
  {
    "size": 2,
    "rep": "SaveData",
    "tokens": [
      "data",
      "save",
      "saved"
    ],
    "members": [
      "SaveData",
      "SavedData"
    ]
  },
  {
    "size": 2,
    "rep": "SceneActivationActionModifier",
    "tokens": [
      "action",
      "activation",
      "deactivation",
      "modifier",
      "scene"
    ],
    "members": [
      "SceneActivationActionModifier",
      "SceneDeactivationActionModifier"
    ]
  },
  {
    "size": 2,
    "rep": "Scheme",
    "tokens": [
      "scheme",
      "schemes"
    ],
    "members": [
      "Scheme",
      "Schemes"
    ]
  },
  {
    "size": 2,
    "rep": "SDK",
    "tokens": [
      "sdk"
    ],
    "members": [
      "SDK",
      "Sdk"
    ]
  },
  {
    "size": 2,
    "rep": "SearchResult",
    "tokens": [
      "result",
      "results",
      "search"
    ],
    "members": [
      "SearchResult",
      "SearchResults"
    ]
  },
  {
    "size": 2,
    "rep": "SectionIndexTitle",
    "tokens": [
      "index",
      "section",
      "title",
      "titles"
    ],
    "members": [
      "SectionIndexTitle",
      "SectionIndexTitles"
    ]
  },
  {
    "size": 2,
    "rep": "Separator",
    "tokens": [
      "separator",
      "separators"
    ],
    "members": [
      "Separator",
      "Separators"
    ]
  },
  {
    "size": 2,
    "rep": "Server",
    "tokens": [
      "server",
      "servers"
    ],
    "members": [
      "Server",
      "Servers"
    ]
  },
  {
    "size": 2,
    "rep": "Session",
    "tokens": [
      "session",
      "sessions"
    ],
    "members": [
      "Session",
      "Sessions"
    ]
  },
  {
    "size": 2,
    "rep": "Setting",
    "tokens": [
      "setting",
      "settings"
    ],
    "members": [
      "Setting",
      "Settings"
    ]
  },
  {
    "size": 2,
    "rep": "SettingButton",
    "tokens": [
      "button",
      "setting",
      "settings"
    ],
    "members": [
      "SettingButton",
      "SettingsButton"
    ]
  },
  {
    "size": 2,
    "rep": "SettingPage",
    "tokens": [
      "page",
      "setting",
      "settings"
    ],
    "members": [
      "SettingPage",
      "SettingsPage"
    ]
  },
  {
    "size": 2,
    "rep": "SettingReducer",
    "tokens": [
      "reducer",
      "setting",
      "settings"
    ],
    "members": [
      "SettingReducer",
      "SettingsReducer"
    ]
  },
  {
    "size": 2,
    "rep": "SettingView",
    "tokens": [
      "setting",
      "settings",
      "view"
    ],
    "members": [
      "SettingView",
      "SettingsView"
    ]
  },
  {
    "size": 2,
    "rep": "SettingView_Previews",
    "tokens": [
      "previews",
      "setting",
      "settings",
      "view"
    ],
    "members": [
      "SettingView_Previews",
      "SettingsView_Previews"
    ]
  },
  {
    "size": 2,
    "rep": "Shadow",
    "tokens": [
      "shadow",
      "shadows"
    ],
    "members": [
      "Shadow",
      "Shadows"
    ]
  },
  {
    "size": 2,
    "rep": "ShareButton",
    "tokens": [
      "button",
      "buttons",
      "share"
    ],
    "members": [
      "ShareButton",
      "ShareButtons"
    ]
  },
  {
    "size": 2,
    "rep": "ShareItem",
    "tokens": [
      "item",
      "items",
      "share"
    ],
    "members": [
      "ShareItem",
      "ShareItems"
    ]
  },
  {
    "size": 2,
    "rep": "SheetView",
    "tokens": [
      "sheet",
      "view",
      "views"
    ],
    "members": [
      "SheetView",
      "SheetViews"
    ]
  },
  {
    "size": 2,
    "rep": "Shortcut",
    "tokens": [
      "shortcut",
      "shortcuts"
    ],
    "members": [
      "Shortcut",
      "Shortcuts"
    ]
  },
  {
    "size": 2,
    "rep": "SidebarTabView_Previews",
    "tokens": [
      "previews",
      "sidebar",
      "tab",
      "view"
    ],
    "members": [
      "SidebarTabView_Previews",
      "SidebarView_Previews"
    ]
  },
  {
    "size": 2,
    "rep": "SignedURL",
    "tokens": [
      "signed",
      "url"
    ],
    "members": [
      "SignedURL",
      "SignedUrl"
    ]
  },
  {
    "size": 2,
    "rep": "Signpost",
    "tokens": [
      "signpost",
      "signposts"
    ],
    "members": [
      "Signpost",
      "Signposts"
    ]
  },
  {
    "size": 2,
    "rep": "Simulator",
    "tokens": [
      "simulator",
      "simulators"
    ],
    "members": [
      "Simulator",
      "Simulators"
    ]
  },
  {
    "size": 2,
    "rep": "SnapshotView",
    "tokens": [
      "snapshot",
      "snapshots",
      "view"
    ],
    "members": [
      "SnapshotView",
      "SnapshotsView"
    ]
  },
  {
    "size": 2,
    "rep": "SpeedMeasurement",
    "tokens": [
      "measurement",
      "measurements",
      "speed"
    ],
    "members": [
      "SpeedMeasurement",
      "SpeedMeasurements"
    ]
  },
  {
    "size": 2,
    "rep": "Static",
    "tokens": [
      "static",
      "statics"
    ],
    "members": [
      "Static",
      "Statics"
    ]
  },
  {
    "size": 2,
    "rep": "Stats",
    "tokens": [
      "stats"
    ],
    "members": [
      "Stats",
      "stats"
    ]
  },
  {
    "size": 2,
    "rep": "STDErrOutputStream",
    "tokens": [
      "output",
      "stderr",
      "stream"
    ],
    "members": [
      "STDErrOutputStream",
      "StderrOutputStream"
    ]
  },
  {
    "size": 2,
    "rep": "Storyboard",
    "tokens": [
      "storyboard",
      "storyboards"
    ],
    "members": [
      "Storyboard",
      "Storyboards"
    ]
  },
  {
    "size": 2,
    "rep": "Stream",
    "tokens": [
      "stream",
      "streams"
    ],
    "members": [
      "Stream",
      "Streams"
    ]
  },
  {
    "size": 2,
    "rep": "Strings",
    "tokens": [
      "strings"
    ],
    "members": [
      "Strings",
      "strings"
    ]
  },
  {
    "size": 2,
    "rep": "Subcomponent",
    "tokens": [
      "subcomponent",
      "subcomponent2"
    ],
    "members": [
      "Subcomponent",
      "Subcomponent2"
    ]
  },
  {
    "size": 2,
    "rep": "Subscribe",
    "tokens": [
      "subscribe",
      "subscriber"
    ],
    "members": [
      "Subscribe",
      "Subscriber"
    ]
  },
  {
    "size": 2,
    "rep": "SUICard",
    "tokens": [
      "suicard",
      "suicards"
    ],
    "members": [
      "SUICard",
      "SUICards"
    ]
  },
  {
    "size": 2,
    "rep": "SwiftPMNode",
    "tokens": [
      "pmnode",
      "pmnodes",
      "swift"
    ],
    "members": [
      "SwiftPMNode",
      "SwiftPMNodes"
    ]
  },
  {
    "size": 2,
    "rep": "SwiftUITabView_Previews",
    "tokens": [
      "previews",
      "swift",
      "uitab",
      "uiview",
      "view"
    ],
    "members": [
      "SwiftUITabView_Previews",
      "SwiftUIView_Previews"
    ]
  },
  {
    "size": 2,
    "rep": "Symbol",
    "tokens": [
      "symbol",
      "symbols"
    ],
    "members": [
      "Symbol",
      "Symbols"
    ]
  },
  {
    "size": 2,
    "rep": "SymbolButton",
    "tokens": [
      "button",
      "buttons",
      "symbol"
    ],
    "members": [
      "SymbolButton",
      "SymbolButtons"
    ]
  },
  {
    "size": 2,
    "rep": "SynchronousOperations",
    "tokens": [
      "operations",
      "options",
      "synchronous"
    ],
    "members": [
      "SynchronousOperations",
      "SynchronousOptions"
    ]
  },
  {
    "size": 2,
    "rep": "TableBackgroundStyle",
    "tokens": [
      "background",
      "key",
      "style",
      "table"
    ],
    "members": [
      "TableBackgroundStyle",
      "TableBackgroundStyleKey"
    ]
  },
  {
    "size": 2,
    "rep": "TableStyle",
    "tokens": [
      "style",
      "styles",
      "table"
    ],
    "members": [
      "TableStyle",
      "TableStyles"
    ]
  },
  {
    "size": 2,
    "rep": "TabTray",
    "tokens": [
      "tab",
      "tabs",
      "tray"
    ],
    "members": [
      "TabTray",
      "TabsTray"
    ]
  },
  {
    "size": 2,
    "rep": "TCPConvenienceOption",
    "tokens": [
      "option",
      "options",
      "tcpconvenience"
    ],
    "members": [
      "TCPConvenienceOption",
      "TCPConvenienceOptions"
    ]
  },
  {
    "size": 2,
    "rep": "TemperatureSensor",
    "tokens": [
      "sensor",
      "sensors",
      "temperature"
    ],
    "members": [
      "TemperatureSensor",
      "TemperatureSensors"
    ]
  },
  {
    "size": 2,
    "rep": "Template",
    "tokens": [
      "template",
      "templates"
    ],
    "members": [
      "Template",
      "Templates"
    ]
  },
  {
    "size": 2,
    "rep": "TextViewSearchContext",
    "tokens": [
      "context",
      "key",
      "search",
      "text",
      "view"
    ],
    "members": [
      "TextViewSearchContext",
      "TextViewSearchContextKey"
    ]
  },
  {
    "size": 2,
    "rep": "Timing",
    "tokens": [
      "timing",
      "timings"
    ],
    "members": [
      "Timing",
      "Timings"
    ]
  },
  {
    "size": 2,
    "rep": "TintColor",
    "tokens": [
      "color",
      "colors",
      "tint"
    ],
    "members": [
      "TintColor",
      "TintColors"
    ]
  },
  {
    "size": 2,
    "rep": "ToastView_Preview",
    "tokens": [
      "preview",
      "previews",
      "toast",
      "view"
    ],
    "members": [
      "ToastView_Preview",
      "ToastView_Previews"
    ]
  },
  {
    "size": 2,
    "rep": "ToolbarButton",
    "tokens": [
      "button",
      "buttons",
      "toolbar"
    ],
    "members": [
      "ToolbarButton",
      "ToolbarButtons"
    ]
  },
  {
    "size": 2,
    "rep": "ToolbarView",
    "tokens": [
      "toolbar",
      "view",
      "views"
    ],
    "members": [
      "ToolbarView",
      "ToolbarViews"
    ]
  },
  {
    "size": 2,
    "rep": "ToolbarVisibility",
    "tokens": [
      "key",
      "toolbar",
      "visibility"
    ],
    "members": [
      "ToolbarVisibility",
      "ToolbarVisibilityKey"
    ]
  },
  {
    "size": 2,
    "rep": "TopSite",
    "tokens": [
      "site",
      "sites",
      "top"
    ],
    "members": [
      "TopSite",
      "TopSites"
    ]
  },
  {
    "size": 2,
    "rep": "TypeAlias",
    "tokens": [
      "alias",
      "type",
      "typealias"
    ],
    "members": [
      "TypeAlias",
      "Typealias"
    ]
  },
  {
    "size": 2,
    "rep": "Update",
    "tokens": [
      "update",
      "updates"
    ],
    "members": [
      "Update",
      "Updates"
    ]
  },
  {
    "size": 2,
    "rep": "UpdateProjectInput",
    "tokens": [
      "input",
      "project",
      "update",
      "v2input"
    ],
    "members": [
      "UpdateProjectInput",
      "UpdateProjectV2Input"
    ]
  },
  {
    "size": 2,
    "rep": "Validation",
    "tokens": [
      "validation",
      "validations"
    ],
    "members": [
      "Validation",
      "Validations"
    ]
  },
  {
    "size": 2,
    "rep": "ValidationError",
    "tokens": [
      "error",
      "validation",
      "validations"
    ],
    "members": [
      "ValidationError",
      "ValidationsError"
    ]
  },
  {
    "size": 2,
    "rep": "ValueTrackConfiguration",
    "tokens": [
      "configuration",
      "key",
      "track",
      "value"
    ],
    "members": [
      "ValueTrackConfiguration",
      "ValueTrackConfigurationKey"
    ]
  },
  {
    "size": 2,
    "rep": "Version",
    "tokens": [
      "s",
      "version"
    ],
    "members": [
      "Version",
      "version_s"
    ]
  },
  {
    "size": 2,
    "rep": "VoteAccount",
    "tokens": [
      "account",
      "accounts",
      "vote"
    ],
    "members": [
      "VoteAccount",
      "VoteAccounts"
    ]
  },
  {
    "size": 2,
    "rep": "Wallpaper",
    "tokens": [
      "wallpaper",
      "wallpapers"
    ],
    "members": [
      "Wallpaper",
      "Wallpapers"
    ]
  },
  {
    "size": 2,
    "rep": "XCAChatGPTApp",
    "tokens": [
      "gptapp",
      "gpttvapp",
      "xcachat"
    ],
    "members": [
      "XCAChatGPTApp",
      "XCAChatGPTTVApp"
    ]
  },
  {
    "size": 2,
    "rep": "XcodeColor",
    "tokens": [
      "color",
      "colors",
      "xcode"
    ],
    "members": [
      "XcodeColor",
      "XcodeColors"
    ]
  },
  {
    "size": 2,
    "rep": "ZhTraditional",
    "tokens": [
      "traditional",
      "v3",
      "zh"
    ],
    "members": [
      "ZhTraditional",
      "ZhTraditional_v3"
    ]
  },
  {
    "size": 2,
    "rep": "Zip3AsyncSequence",
    "tokens": [
      "async",
      "sequence",
      "zip",
      "zip3async"
    ],
    "members": [
      "Zip3AsyncSequence",
      "ZipAsyncSequence"
    ]
  },
  {
    "size": 2,
    "rep": "zzz_DflatGen_MyGame_SampleV2_Empty",
    "tokens": [
      "dflat",
      "empty",
      "game",
      "gen",
      "my",
      "sample",
      "v2",
      "v3",
      "zzz"
    ],
    "members": [
      "zzz_DflatGen_MyGame_SampleV2_Empty",
      "zzz_DflatGen_MyGame_SampleV3_Empty"
    ]
  }
]